code_roast_bot/__init__.py
code_roast_bot/main.py
code_roast_bot/prompt_templates.py
code_roast_bot/utils.py
code_roast_bot-1.6.0.dist-info/licenses/LICENSE
code_roast_bot-1.6.0.dist-info/METADATA
code_roast_bot-1.6.0.dist-info/WHEEL
code_roast_bot-1.6.0.dist-info/entry_points.txt
code_roast_bot-1.6.0.dist-info/top_level.txt
code_roast_bot-1.6.0.dist-info/RECORD
