Metadata-Version: 2.4
Name: code_roast_bot
Version: 1.6.0
Summary: A sarcastic and secure GPT-powered Python code roaster.
Home-page: https://github.com/yourusername/code-roast-bot
Author: Benjamin Lyon
Author-email: blyon@mindtunnel.net
License: BSD-3-Clause
Classifier: Development Status :: 5 - Production/Stable
Classifier: Intended Audience :: Developers
Classifier: Programming Language :: Python :: 3.8
Classifier: License :: OSI Approved :: BSD License
Classifier: Topic :: Software Development :: Code Generators
Classifier: Topic :: Security
Requires-Python: >=3.8
License-File: LICENSE
Requires-Dist: openai==1.78.1
Requires-Dist: python-dotenv==1.0.1
Requires-Dist: tiktoken==0.9.0
Requires-Dist: tenacity==9.1.2
Requires-Dist: colorama==0.4.6
Dynamic: author
Dynamic: author-email
Dynamic: classifier
Dynamic: description
Dynamic: description-content-type
Dynamic: home-page
Dynamic: license
Dynamic: license-file
Dynamic: requires-dist
Dynamic: requires-python
Dynamic: summary
